setup.py
s3compress/__init__.py
s3compress/main.py
s3compress.egg-info/PKG-INFO
s3compress.egg-info/SOURCES.txt
s3compress.egg-info/dependency_links.txt
s3compress.egg-info/entry_points.txt
s3compress.egg-info/not-zip-safe
s3compress.egg-info/requires.txt
s3compress.egg-info/top_level.txt