Metadata-Version: 1.0
Name: s3compress
Version: 0.0.3
Summary: compress files on s3 prefix
Home-page: https://pip.pypa.io/
Author: Padmakar Ojha
Author-email: padmakarojha@gmail.com
License: UNKNOWN
Keywords: s3 compress
Platform: UNKNOWN
